docs/conf_common.py
docs/en/conf.py
esp_idf_kconfig/__init__.py
esp_idf_kconfig/__main__.py
esp_idf_kconfig/gen_kconfig_doc.py
esp_kconfiglib/__init__.py
esp_kconfiglib/constants.py
esp_kconfiglib/core.py
esp_kconfiglib/kconfig_grammar.py
esp_kconfiglib/kconfig_parser.py
esp_kconfiglib/report.py
esp_menuconfig/__init__.py
esp_menuconfig/__main__.py
esp_menuconfig/core.py
kconfcheck/__init__.py
kconfcheck/__main__.py
kconfcheck/check_deprecated_options.py
kconfcheck/core.py
kconfgen/__init__.py
kconfgen/__main__.py
kconfgen/core.py
kconfiglib/__init__.py
kconfserver/__init__.py
kconfserver/__main__.py
kconfserver/core.py
menuconfig/__init__.py
menuconfig/__main__.py
esp_idf_kconfig-3.4.2.dist-info/LICENSE
esp_idf_kconfig-3.4.2.dist-info/METADATA
esp_idf_kconfig-3.4.2.dist-info/WHEEL
esp_idf_kconfig-3.4.2.dist-info/top_level.txt
esp_idf_kconfig-3.4.2.dist-info/RECORD
