Metadata-Version: 2.1
Name: esp-idf-kconfig
Version: 3.4.2
Summary: Kconfig tooling for esp-idf
Author: Espressif Systems
License: 
Project-URL: Homepage, https://github.com/espressif/esp-idf-kconfig
Keywords: espressif,embedded,project,configuration,kconfig
Classifier: Development Status :: 5 - Production/Stable
Classifier: Intended Audience :: Developers
Classifier: Natural Language :: English
Classifier: Environment :: Console
Classifier: Topic :: Software Development :: Embedded Systems
Classifier: License :: OSI Approved :: Apache Software License
Classifier: Programming Language :: Python :: 3.8
Classifier: Programming Language :: Python :: 3.9
Classifier: Programming Language :: Python :: 3.10
Classifier: Programming Language :: Python :: 3.11
Classifier: Programming Language :: Python :: 3.12
Classifier: Programming Language :: Python :: 3.13
Classifier: Programming Language :: Python :: 3.14
Classifier: Operating System :: POSIX
Classifier: Operating System :: Microsoft :: Windows
Classifier: Operating System :: MacOS :: MacOS X
Requires-Python: >=3.8
License-File: LICENSE
Requires-Dist: rich
Requires-Dist: pyparsing
Requires-Dist: windows-curses ; sys_platform == "win32" and python_version < "3.13"
Requires-Dist: windows-curses >=2.4.1 ; sys_platform == "win32" and python_version >= "3.13"
Provides-Extra: dev
Requires-Dist: pre-commit ; extra == 'dev'
Requires-Dist: pexpect ; extra == 'dev'
Requires-Dist: pytest ; extra == 'dev'
Requires-Dist: coverage[toml] ; extra == 'dev'
Requires-Dist: czespressif ; (python_version >= "3.9") and extra == 'dev'
Provides-Extra: docs
Requires-Dist: esp-docs ; extra == 'docs'
